[{
    "qatariId": 12,
    "firstName": "Juha",
    "lastName": "Dahak",
    "mobile": "7777-888",
    "email": "juha@test.com",
    "username": "juha",
    "password": "password",
    "students": [{
        "studentId": 1,
        "firstName": "Ibn Juha",
        "lastName": "Dahak",
        "dob": "1/1/2009",
        "gender": "M",
        "schoolGrade": 4,
        "teacherId": 501
      },
      {
        "studentId": 2,
        "firstName": "Bint Juha",
        "lastName": "Dahak",
        "dob": "1/5/2011",
        "gender": "F",
        "schoolGrade": 2,
        "teacherId": 502
      }
    ]
  },
  {
    "qatariId": 34,
    "firstName": "Abbas",
    "lastName": "Ibn Firnas",
    "mobile": "9999-888",
    "email": "abbas@test.com",
    "username": "abbas",
    "password": "password",
    "students": [{
        "studentId": 3,
        "firstName": "Ibn Abbas",
        "lastName": "Ibn Firnas",
        "dob": "1/2/2008",
        "gender": "M",
        "schoolGrade": 5,
        "teacherId": 501
      },
      {
        "studentId": 4,
        "firstName": "Bint Abbas",
        "lastName": "Ibn Firnas",
        "dob": "1/3/2012",
        "gender": "F",
        "schoolGrade": 2,
        "teacherId": 502
      }
    ]
  },
  {
    "qatariId": 56,
    "firstName": "Samira",
    "lastName": "Saghir",
    "mobile": "9999-888",
    "email": "samira@test.com",
    "username": "samira",
    "password": "password",
    "students": [{
        "studentId": 5,
        "firstName": "Ibn Samira",
        "lastName": "Saghir",
        "dob": "1/2/2007",
        "gender": "M",
        "schoolGrade": 6,
        "teacherId": 501
      },
      {
        "studentId": 6,
        "firstName": "Bint Samira",
        "lastName": "Saghir",
        "dob": "1/3/2010",
        "gender": "F",
        "schoolGrade": 3,
        "teacherId": 502
      }
    ]
  }
]